{
"type": "FeatureCollection",
"name": "geo_03_特定施設入居者生活介護（有料老人ホーム）",
"crs": { "type": "name", "properties": { "name": "urn:ogc:def:crs:OGC:1.3:CRS84" } },
"features": [
{ "type": "Feature", "properties": { "内容": "福寿の森【特定施設入居者生活介護（有料老人ホーム）】岩手県盛岡市本宮6丁目1-47福寿の森", "url": "https://www.kaigokensaku.mhlw.go.jp/03/index.php?action_kouhyou_detail_004_kani=true&JigyosyoCd=370107385-00&ServiceCd=331&Type=search", "url2": null }, "geometry": { "type": "Point", "coordinates": [ 141.1253213, 39.6880351 ] } },
{ "type": "Feature", "properties": { "内容": "介護付有料老人ホームやすらぎ【特定施設入居者生活介護（有料老人ホーム）】岩手県盛岡市繋字猿田１番地４６", "url": "https://www.kaigokensaku.mhlw.go.jp/03/index.php?action_kouhyou_detail_004_kani=true&JigyosyoCd=372101444-00&ServiceCd=331&Type=search", "url2": "https://www.yasuragi-home.jp" }, "geometry": { "type": "Point", "coordinates": [ 141.026501200000013, 39.6804712 ] } },
{ "type": "Feature", "properties": { "内容": "介護付有料老人ホームあおぞら【特定施設入居者生活介護（有料老人ホーム）】岩手県盛岡市津志田町一丁目15番37号", "url": "https://www.kaigokensaku.mhlw.go.jp/03/index.php?action_kouhyou_detail_004_kani=true&JigyosyoCd=370106460-00&ServiceCd=331&Type=search", "url2": "http://medical-sp.jp/" }, "geometry": { "type": "Point", "coordinates": [ 141.153440466271007, 39.668210930035698 ] } },
{ "type": "Feature", "properties": { "内容": "アンビシャスシティ志家【特定施設入居者生活介護（有料老人ホーム）】岩手県盛岡市中ノ橋通２丁目７－３８", "url": "https://www.kaigokensaku.mhlw.go.jp/03/index.php?action_kouhyou_detail_004_kani=true&JigyosyoCd=370103772-00&ServiceCd=331&Type=search", "url2": "http://www.ambitious-city.co.jp/" }, "geometry": { "type": "Point", "coordinates": [ 141.1611389, 39.6979981 ] } },
{ "type": "Feature", "properties": { "内容": "盛岡北ケアコミュニティそよ風【特定施設入居者生活介護（有料老人ホーム）】岩手県盛岡市三ツ割4丁目7-17", "url": "https://www.kaigokensaku.mhlw.go.jp/03/index.php?action_kouhyou_detail_004_kani=true&JigyosyoCd=370107195-00&ServiceCd=331&Type=search", "url2": null }, "geometry": { "type": "Point", "coordinates": [ 141.1577996, 39.7297717 ] } },
{ "type": "Feature", "properties": { "内容": "介護付き有料老人ホーム「百万石」【特定施設入居者生活介護（有料老人ホーム）】岩手県盛岡市本宮３丁目9-2", "url": "https://www.kaigokensaku.mhlw.go.jp/03/index.php?action_kouhyou_detail_004_kani=true&JigyosyoCd=370107922-00&ServiceCd=331&Type=search", "url2": "https://genkinakaigo.co.jp/" }, "geometry": { "type": "Point", "coordinates": [ 141.13340475582001, 39.6931831277887 ] } },
{ "type": "Feature", "properties": { "内容": "介護付き有料老人ホームホープタウン輪っか【特定施設入居者生活介護（有料老人ホーム）】岩手県盛岡市津志田西2丁目2-51ホープタウン輪っか", "url": "https://www.kaigokensaku.mhlw.go.jp/03/index.php?action_kouhyou_detail_004_kani=true&JigyosyoCd=370107229-00&ServiceCd=331&Type=search", "url2": "http://www.hopetown-wakka.com" }, "geometry": { "type": "Point", "coordinates": [ 141.149463, 39.666238 ] } },
{ "type": "Feature", "properties": { "内容": "ブライトステージ【特定施設入居者生活介護（有料老人ホーム）】岩手県盛岡市肴町３番１８号", "url": "https://www.kaigokensaku.mhlw.go.jp/03/index.php?action_kouhyou_detail_004_kani=true&JigyosyoCd=370103327-00&ServiceCd=331&Type=search", "url2": "http://www.brightstage.co.jp" }, "geometry": { "type": "Point", "coordinates": [ 141.1540034, 39.6993922 ] } },
{ "type": "Feature", "properties": { "内容": "介護付有料老人ホ－ムいわいの郷【特定施設入居者生活介護（有料老人ホーム）】岩手県一関市山目字館６４番７", "url": "https://www.kaigokensaku.mhlw.go.jp/03/index.php?action_kouhyou_detail_004_kani=true&JigyosyoCd=370900979-00&ServiceCd=331&Type=search", "url2": "https://i3syukai.com" }, "geometry": { "type": "Point", "coordinates": [ 141.117020599999989, 38.9407671 ] } }
]
}
